slise/__init__.py
slise/data.py
slise/initialisation.py
slise/optimisation.py
slise/plot.py
slise/slise.py
slise/utils.py
slise-2.2.4.dist-info/LICENSE
slise-2.2.4.dist-info/METADATA
slise-2.2.4.dist-info/WHEEL
slise-2.2.4.dist-info/top_level.txt
slise-2.2.4.dist-info/RECORD
