Metadata-Version: 2.1
Name: slise
Version: 2.2.4
Summary: The SLISE algorithm for robust regression and explanations of black box models
Author-email: Anton Björklund <anton.bjorklund@helsinki.fi>
License: MIT License
Project-URL: homepage, https://edahelsinki.fi/pyslise
Project-URL: documentation, https://edahelsinki.fi/pyslise/docs/slise/
Project-URL: repository, https://github.com/edahelsinki/pyslise.git
Keywords: Robust regression,Sparse Linear Regression,Explainable Artificial Intelligence,Local Explanations
Classifier: Programming Language :: Python :: 3
Classifier: License :: OSI Approved :: MIT License
Classifier: Operating System :: OS Independent
Classifier: Topic :: Scientific/Engineering :: Artificial Intelligence
Classifier: Topic :: Scientific/Engineering :: Visualization
Requires-Python: >=3.6
License-File: LICENSE
Requires-Dist: numpy >=1.20
Requires-Dist: scipy >=1.6
Requires-Dist: numba >=0.53
Requires-Dist: matplotlib >=3.3
Requires-Dist: PyLBFGS >=0.2
Provides-Extra: dev
Requires-Dist: pytest ; extra == 'dev'
Requires-Dist: pytest-cov ; extra == 'dev'
Requires-Dist: black[jupyter] ; extra == 'dev'
Requires-Dist: pylint ; extra == 'dev'
Requires-Dist: IPython ; extra == 'dev'
Requires-Dist: ruff ; extra == 'dev'
Provides-Extra: tbb
Requires-Dist: tbb ; extra == 'tbb'
